com/__init__.py
com/dvsnier/__init__.py
com/dvsnier/http/__init__.py
com/dvsnier/http/analysis/__init__.py
com/dvsnier/http/analysis/analysis_factory.py
com/dvsnier/http/analysis/adapter/__init__.py
com/dvsnier/http/analysis/adapter/abstract_adapter.py
com/dvsnier/http/analysis/adapter/idapter.py
com/dvsnier/http/analysis/model/__init__.py
com/dvsnier/http/analysis/model/abstract_model.py
com/dvsnier/http/analysis/model/comment_model.py
com/dvsnier/http/analysis/model/imodel.py
com/dvsnier/http/analysis/model/meta_model.py
com/dvsnier/http/analysis/model/node_model.py
com/dvsnier/http/analysis/model/publisher_model.py
com/dvsnier/http/analysis/model/respondent_model.py
com/dvsnier/http/analysis/resolver/__init__.py
com/dvsnier/http/analysis/resolver/abstract_resolver.py
com/dvsnier/http/analysis/resolver/iresolver.py
com/dvsnier/http/analysis/resolver/simple_resolver.py
com/dvsnier/http/analysis/rma/__init__.py
com/dvsnier/http/analysis/rma/abstract_rma.py
com/dvsnier/http/analysis/rma/irma.py
com/dvsnier/http/base/__init__.py
com/dvsnier/http/base/abstract_http.py
com/dvsnier/http/base/ihttp.py
com/dvsnier/http/bbs/__init__.py
com/dvsnier/http/bbs/specimen/__init__.py
com/dvsnier/http/bbs/specimen/bbs_with_tianya.py
com/dvsnier/http/bbs/specimen/tianya/__init__.py
com/dvsnier/http/bbs/specimen/tianya/api_internal_tianya.py
com/dvsnier/http/bbs/specimen/tianya/api_tianya.py
com/dvsnier/http/bbs/specimen/tianya/tianya_adapter.py
com/dvsnier/http/command/__init__.py
com/dvsnier/http/command/dvs_sniffer.py
com/dvsnier/http/config/__init__.py
com/dvsnier/http/config/bbs_plate_with_ty.py
com/dvsnier/http/config/iconfig.py
com/dvsnier/http/dom/__init__.py
com/dvsnier/http/dom/abstract_dom.py
com/dvsnier/http/dom/common_dom.py
com/dvsnier/http/dom/idom.py
com/dvsnier/http/dom/attribute/__init__.py
com/dvsnier/http/dom/attribute/abstract_attribute.py
com/dvsnier/http/dom/attribute/iattribute.py
com/dvsnier/http/dom/content/__init__.py
com.dvsnier.sniffer-0.0.1a2.dev2.dist-info/LICENSE
com.dvsnier.sniffer-0.0.1a2.dev2.dist-info/LICENSE.txt
com.dvsnier.sniffer-0.0.1a2.dev2.dist-info/METADATA
com.dvsnier.sniffer-0.0.1a2.dev2.dist-info/WHEEL
com.dvsnier.sniffer-0.0.1a2.dev2.dist-info/entry_points.txt
com.dvsnier.sniffer-0.0.1a2.dev2.dist-info/top_level.txt
com.dvsnier.sniffer-0.0.1a2.dev2.dist-info/RECORD
